{
  "schema_version": "1.0",
  "category": "密教教学用語（mikkyo terms）",
  "source_corpus": "hizo-houyaku.json",
  "corpus_type": "dict",
  "extraction_field": "gendaigoyaku",
  "generated_at": "2026-05-03",
  "extraction_strategy": "辞書ベース（19 語）+ 長語優先 substring 走査 + 周辺梵語注記抽出",
  "dictionary_size": 19,
  "gendaigoyaku_length": 75246,
  "summary": {
    "unique_terms": 19,
    "total_occurrences": 257,
    "kaimyo_suitable_count": 11,
    "matched_term_count": 13
  },
  "entries": [
    {
      "term": "大日",
      "term_kana": "",
      "sanskrit": "Mahāvairocana",
      "definition": "大日如来。密教の本尊。遮那と同義。法身そのもの。",
      "kaimyo_suitable": true,
      "kaimyo_chars": [
        "大",
        "日"
      ],
      "occurrence_count": 62,
      "occurrences": [
        {
          "corpus_id": "hizo-houyaku",
          "context": "典や論書に書かれていますが、詳しいことは後に述べましょう。 大日如来に帰依 七言の頌で申します。 初めに種々のものを形成する",
          "context_position": 3828,
          "sanskrit_in_context": []
        },
        {
          "corpus_id": "hizo-houyaku",
          "context": "する原点としての能生である地・水・火・風・空・識の六大の仏（大日如来のこと）〔＊〕に帰依し奉ります。また、大日如来が種々の形",
          "context_position": 3888,
          "sanskrit_in_context": []
        },
        {
          "corpus_id": "hizo-houyaku",
          "context": "識の六大の仏（大日如来のこと）〔＊〕に帰依し奉ります。また、大日如来が種々の形をとって現われた所生である四種の曼荼羅に帰依し",
          "context_position": 3911,
          "sanskrit_in_context": []
        },
        {
          "corpus_id": "hizo-houyaku",
          "context": "示される仏・菩薩です。これをサマヤマンダラといいます。第三に大日如来を囲む金剛薩埵等の四菩薩とその四尊を供養する四菩薩女等で",
          "context_position": 4051,
          "sanskrit_in_context": []
        },
        {
          "corpus_id": "hizo-houyaku",
          "context": "整然と碍りなく並んでおり、その数は無数で、かつすべては中央の大日如来の変化した姿なのです。 私はいま、淳和天皇の詔命を承けて",
          "context_position": 4206,
          "sanskrit_in_context": []
        },
        {
          "corpus_id": "hizo-houyaku",
          "context": "なたも、毎日が新しい生活になることでしょう。 ＊六大の仏……大日如来の本性は六大という六つの本質で構成され、あらゆるものの当",
          "context_position": 4383,
          "sanskrit_in_context": []
        },
        {
          "corpus_id": "hizo-houyaku",
          "context": "六大能生という。漢文で「六大能く……を生ず」から主体としての大日を六大能生と表現するのである。その大日如来が、あらゆる形で現",
          "context_position": 4452,
          "sanskrit_in_context": []
        },
        {
          "corpus_id": "hizo-houyaku",
          "context": "生ず」から主体としての大日を六大能生と表現するのである。その大日如来が、あらゆる形で現われることを所生の四種曼荼羅という。以",
          "context_position": 4471,
          "sanskrit_in_context": []
        },
        {
          "corpus_id": "hizo-houyaku",
          "context": "ういう経典によってこの教えを建てるのですか。 答う、それは『大日経』です。 問う、その経になんと説いているのですか。 答う、",
          "context_position": 8918,
          "sanskrit_in_context": []
        },
        {
          "corpus_id": "hizo-houyaku",
          "context": "』です。 問う、その経になんと説いているのですか。 答う、『大日経』の住心品にこう言っています、「秘密主よ、無始の生死の中に",
          "context_position": 8951,
          "sanskrit_in_context": []
        },
        {
          "corpus_id": "hizo-houyaku",
          "context": "したいという心が生じてくるのです。 私たちの善心の種子は、『大日経疏』に記されているように、まず芽を出し、次にふくらんで、や",
          "context_position": 10342,
          "sanskrit_in_context": []
        },
        {
          "corpus_id": "hizo-houyaku",
          "context": "住心はどの経典によって説かれているのですか。 答う、それは『大日経』です。 その経典になんと書いてあるのですか。 『大日経』",
          "context_position": 12332,
          "sanskrit_in_context": []
        },
        {
          "corpus_id": "hizo-houyaku",
          "context": "は『大日経』です。 その経典になんと書いてあるのですか。 『大日経』住心品にこう言っています、「愚童・凡夫にも、ある時ふと、",
          "context_position": 12360,
          "sanskrit_in_context": []
        },
        {
          "corpus_id": "hizo-houyaku",
          "context": "は一切の徳を備えておられ一切の教えのそれぞれの教主なのです。大日如来は、相手の好みや力量に応じてそれぞれの教えを説かれて衆生",
          "context_position": 13813,
          "sanskrit_in_context": []
        },
        {
          "corpus_id": "hizo-houyaku",
          "context": "の教えを説かれて衆生を済度されているのです。 経典の典拠 『大日経』にこう説いています、「如来・応供・正遍智（仏の十号といっ",
          "context_position": 13865,
          "sanskrit_in_context": []
        },
        {
          "corpus_id": "hizo-houyaku",
          "context": "すと、声聞乗・縁覚乗・大乗の教え、及び人乗・天乗はみな一人の大日如来が説かれた教えなのです。したがってどの教えにしたがおうと",
          "context_position": 14156,
          "sanskrit_in_context": []
        },
        {
          "corpus_id": "hizo-houyaku",
          "context": "どのような経典・論書によって説かれているのですか。 答う、『大日経』と『菩提心論』とです。 その経に何と説いているのですか。",
          "context_position": 17423,
          "sanskrit_in_context": []
        },
        {
          "corpus_id": "hizo-houyaku",
          "context": "と『菩提心論』とです。 その経に何と説いているのですか。 『大日経』住心品に次のように云っています、 「秘密主よ、彼らは戒を",
          "context_position": 17457,
          "sanskrit_in_context": []
        },
        {
          "corpus_id": "hizo-houyaku",
          "context": "阿羅漢という聖者になることができるでありましょう── また『大日経』具縁品にはこうも言っています、 「秘密主よ、世間の因果と",
          "context_position": 18397,
          "sanskrit_in_context": []
        },
        {
          "corpus_id": "hizo-houyaku",
          "context": "の内容をいう時に用いられる。 声聞乗の教理 そこで大覚世尊（大日如来）は羊車の教え（『法華経』で声聞乗を羊車にたとえるところ",
          "context_position": 19525,
          "sanskrit_in_context": []
        },
        {
          "corpus_id": "hizo-houyaku",
          "context": "ずらわしさの中に輪廻転生してゆくばかりです。それゆえに大聖（大日如来）は羊車の教え（声聞乗・前出）をここに開示されたのです。",
          "context_position": 21937,
          "sanskrit_in_context": []
        },
        {
          "corpus_id": "hizo-houyaku",
          "context": "問う、この住心はどの経論によって建立するのですか。 答う、『大日経』と『菩提心論』とによっています。 その経論に何と説いてい",
          "context_position": 22304,
          "sanskrit_in_context": []
        },
        {
          "corpus_id": "hizo-houyaku",
          "context": "』とによっています。 その経論に何と説いているのですか。 『大日経』住心品にこういっています、「謂く、この人たちは、唯蘊無我",
          "context_position": 22344,
          "sanskrit_in_context": []
        },
        {
          "corpus_id": "hizo-houyaku",
          "context": "を第十地という。 ◇ これらに対して密教とは、自性法身である大日如来がお説きになった教えです。この如来が御自分の眷属とご一緒",
          "context_position": 33312,
          "sanskrit_in_context": []
        },
        {
          "corpus_id": "hizo-houyaku",
          "context": "て、寂滅の心境を身に悟るだけのものといえましょう。それゆえ『大日経』の住心品にこう言っています、「業・煩悩の株杌と無明の種子",
          "context_position": 40465,
          "sanskrit_in_context": []
        },
        {
          "corpus_id": "hizo-houyaku",
          "context": "の世を継続せしめていく要因）を抜き去ります」と。 また同じ『大日経』の入曼荼羅具縁品にこう言っています、「このうち辟支仏（縁",
          "context_position": 40550,
          "sanskrit_in_context": []
        },
        {
          "corpus_id": "hizo-houyaku",
          "context": "第五住心はいずれの経論によって説いているのですか。 答う、『大日経』と『菩提心論』とです。 それらの経論に何と説いているので",
          "context_position": 43012,
          "sanskrit_in_context": []
        },
        {
          "corpus_id": "hizo-houyaku",
          "context": "提心論』とです。 それらの経論に何と説いているのですか。 『大日経』住心品にこう言っています、「縁覚乗の者は、業・煩悩の株杌",
          "context_position": 43049,
          "sanskrit_in_context": []
        },
        {
          "corpus_id": "hizo-houyaku",
          "context": "、この住心は何という経論に依って建立したのですか。 答う、『大日経』と『菩提心論』等によっています。 問う、その経論等に何と",
          "context_position": 48277,
          "sanskrit_in_context": []
        },
        {
          "corpus_id": "hizo-houyaku",
          "context": "ます。 問う、その経論等に何と説いているのですか。 答う、『大日経』住心品に次のように言っています、「秘密主よ、大乗の教えを",
          "context_position": 48324,
          "sanskrit_in_context": []
        },
        {
          "corpus_id": "hizo-houyaku",
          "context": "宗、いわゆる南宗の綱領なのです。 第七住心の名前 それ故に『大日経』住心品の中で大日如来は秘密主（金剛手菩薩・金剛薩埵）にこ",
          "context_position": 51192,
          "sanskrit_in_context": []
        },
        {
          "corpus_id": "hizo-houyaku",
          "context": "領なのです。 第七住心の名前 それ故に『大日経』住心品の中で大日如来は秘密主（金剛手菩薩・金剛薩埵）にこう告げられました、「",
          "context_position": 51202,
          "sanskrit_in_context": []
        },
        {
          "corpus_id": "hizo-houyaku",
          "context": "本体などというものは把握できないものなのです」と。 さらに『大日経疏』にはこの文を釈してこういっています、「ここで心主といっ",
          "context_position": 51358,
          "sanskrit_in_context": []
        },
        {
          "corpus_id": "hizo-houyaku",
          "context": "の典拠 前の覚心不生の名称を説明した文の続きになりますが、『大日経』住心品に次のように言っています、「秘密主よ、彼はこのよう",
          "context_position": 52661,
          "sanskrit_in_context": []
        },
        {
          "corpus_id": "hizo-houyaku",
          "context": "て、これを「菩提」とするのです。 第八住心の典拠 それゆえ『大日経』住心品の中で大日如来は秘密主（金剛薩埵）に告げてこう言っ",
          "context_position": 56539,
          "sanskrit_in_context": []
        },
        {
          "corpus_id": "hizo-houyaku",
          "context": "するのです。 第八住心の典拠 それゆえ『大日経』住心品の中で大日如来は秘密主（金剛薩埵）に告げてこう言っておられます。 「秘",
          "context_position": 56549,
          "sanskrit_in_context": []
        },
        {
          "corpus_id": "hizo-houyaku",
          "context": "の教えと比べてみれば、こうした考えはまだ入口にすぎません。『大日経』でもそう言っておりますし、『大智度論』でもそう述べている",
          "context_position": 58183,
          "sanskrit_in_context": []
        },
        {
          "corpus_id": "hizo-houyaku",
          "context": "もそう述べているのですから疑う余地はありません。 さらに、『大日経』の、先に挙げた文について、『大日経疏』では次のように説明",
          "context_position": 58237,
          "sanskrit_in_context": []
        },
        {
          "corpus_id": "hizo-houyaku",
          "context": "ありません。 さらに、『大日経』の、先に挙げた文について、『大日経疏』では次のように説明しています、「謂う所の空性（空観を体",
          "context_position": 58255,
          "sanskrit_in_context": []
        },
        {
          "corpus_id": "hizo-houyaku",
          "context": "れています」と。この文は理法身〔＊〕を明かしたものです。 『大日経疏』ではさらにこう言います、「行者がこの心に住する時に、次",
          "context_position": 58403,
          "sanskrit_in_context": []
        },
        {
          "corpus_id": "hizo-houyaku",
          "context": "金剛手秘密主、秘密主、金剛手、これらは皆同じ菩薩で、密教では大日如来の教えを承ける菩薩として重要な役目を持っている。 ＊一切",
          "context_position": 58720,
          "sanskrit_in_context": []
        },
        {
          "corpus_id": "hizo-houyaku",
          "context": "智ですべて一切を知ることができる、ということであるが、密教で大日如来は、マンダラ上で四仏にとりかこまれて五仏となり、同時に五",
          "context_position": 58798,
          "sanskrit_in_context": []
        },
        {
          "corpus_id": "hizo-houyaku",
          "context": "方八方にひろがり、虚空に遍満している。このような広がりを持つ大日如来の智を、一切智智という。マンダラを頭に置いて理解する必要",
          "context_position": 58918,
          "sanskrit_in_context": []
        },
        {
          "corpus_id": "hizo-houyaku",
          "context": "は、法身を人格的にとらえようとする考え方による。空海上人は、大日如来を理智法身の境界と言っている。 第八住心の主張者 隋の天",
          "context_position": 59045,
          "sanskrit_in_context": []
        },
        {
          "corpus_id": "hizo-houyaku",
          "context": "す。その仏は、身・心ともに滅して虚空と等同なのですが、応化（大日如来の本体ではなく、他のお姿に現じている仏身）の仏身ですから",
          "context_position": 59504,
          "sanskrit_in_context": []
        },
        {
          "corpus_id": "hizo-houyaku",
          "context": "界、即ち華厳三昧の大意であります。 第九住心の典拠（一） 『大日経』住心品の中で毘盧舎那仏は秘密主に対して次のように告げてお",
          "context_position": 63582,
          "sanskrit_in_context": []
        },
        {
          "corpus_id": "hizo-houyaku",
          "context": "（極めて自性の無い心）が生じます」と。 そして善無畏三蔵は『大日経疏』の中でこう説明しています。 「この極無自性心という一句",
          "context_position": 63738,
          "sanskrit_in_context": []
        },
        {
          "corpus_id": "hizo-houyaku",
          "context": "わしている。法界縁起がこれである。 第九住心の典拠（二） 『大日経』の住心品にこう言っています、「有為（常に変りゆく世界）と",
          "context_position": 64794,
          "sanskrit_in_context": []
        },
        {
          "corpus_id": "hizo-houyaku",
          "context": "になってさらに六年間苦行を続けましたが、私は無上の正覚を得て大日如来になることはできませんでした。そして道場に坐っていた時に",
          "context_position": 65610,
          "sanskrit_in_context": []
        },
        {
          "corpus_id": "hizo-houyaku",
          "context": "因となっているのです。 しかしこの第十住心の真言密教は、法身大日如来の説であり、秘密金剛の教えで、最もすぐれた真実の生きかた",
          "context_position": 67657,
          "sanskrit_in_context": []
        },
        {
          "corpus_id": "hizo-houyaku",
          "context": "をこの自身に体現することができるのです。 第十住心の典拠 『大日経』住心品にこう言っています、「また次に秘密主よ。真言密教に",
          "context_position": 68023,
          "sanskrit_in_context": []
        },
        {
          "corpus_id": "hizo-houyaku",
          "context": "に入る菩薩の功徳を讃歎しているという意味であります。 また『大日経』（入曼荼羅品）にこう言っています、「その時に毘盧遮那世尊",
          "context_position": 68219,
          "sanskrit_in_context": []
        },
        {
          "corpus_id": "hizo-houyaku",
          "context": "るのでなければ、明らかにすることは難しいのです。また、この『大日経』には、百字輪とか十二字などの真言の観法や三摩地法門があり",
          "context_position": 68494,
          "sanskrit_in_context": []
        },
        {
          "corpus_id": "hizo-houyaku",
          "context": "三十七尊とか、四智印の三摩地等があります。すなわちこれらは、大日如来の極秘密三昧なのです。意味は広大ですから、直接会って伝え",
          "context_position": 68571,
          "sanskrit_in_context": []
        },
        {
          "corpus_id": "hizo-houyaku",
          "context": "であります。 金剛界三十七尊 三十七尊について言えば、中央の大日如来とその四方をとり囲む、いわゆる五仏は各々一つの智慧を表わ",
          "context_position": 69608,
          "sanskrit_in_context": []
        },
        {
          "corpus_id": "hizo-houyaku",
          "context": "それが羯磨部の智なるがゆえに、羯磨智と名づけるのです。中央の大日如来・毘盧遮那仏は、法界体性智を成ずるに由るもので、これを根",
          "context_position": 69885,
          "sanskrit_in_context": []
        },
        {
          "corpus_id": "hizo-houyaku",
          "context": "、一切諸法の、本より不生不滅なる義を示すものであります。 『大日経疏』第十四によると、この阿字を釈するのに五通りあります。一",
          "context_position": 70709,
          "sanskrit_in_context": []
        },
        {
          "corpus_id": "hizo-houyaku",
          "context": "ばなりません。 第十住心の典拠 このゆえに『大毘盧遮那経』（大日経）にこう言っています、〈悉地は心より生ず〉と。 また『金剛",
          "context_position": 72908,
          "sanskrit_in_context": []
        },
        {
          "corpus_id": "hizo-houyaku",
          "context": "。もし根本の菩提心に帰してみれば、衆生の世界が即ち密厳国土（大日如来の仏国土）であります。この座を起たずしてそのまま、よく一",
          "context_position": 73324,
          "sanskrit_in_context": []
        },
        {
          "corpus_id": "hizo-houyaku",
          "context": "す。このゆえに、この世の人々を救済するために応化（本体である大日如来が種々の諸尊に身を変えて種々の人々を救済する、これを応化",
          "context_position": 73947,
          "sanskrit_in_context": []
        },
        {
          "corpus_id": "hizo-houyaku",
          "context": "う二つの秘蔵（秘密の蔵で真言密教を指す）は、これだけが、法身大日如来のお説きになった教えなのです。この大日如来が、自分の眷族",
          "context_position": 75041,
          "sanskrit_in_context": []
        },
        {
          "corpus_id": "hizo-houyaku",
          "context": "、これだけが、法身大日如来のお説きになった教えなのです。この大日如来が、自分の眷族である四種法身の仏・菩薩と共に、金剛法界宮",
          "context_position": 75062,
          "sanskrit_in_context": []
        }
      ]
    },
    {
      "term": "真言",
      "term_kana": "",
      "sanskrit": "mantra",
      "definition": "真言陀羅尼。仏の真実言語。密教修行の中心。",
      "kaimyo_suitable": true,
      "kaimyo_chars": [
        "真",
        "言"
      ],
      "occurrence_count": 40,
      "occurrences": [
        {
          "corpus_id": "hizo-houyaku",
          "context": "れを顕教という）は、宮殿の外側の塵を払っているようなもので、真言密教こそが、宝の宮殿の鍵をあけて、中の宝物を手に入れることが",
          "context_position": 3528,
          "sanskrit_in_context": []
        },
        {
          "corpus_id": "hizo-houyaku",
          "context": "しめを受けてさらに次に進んで行くのです。 第十、秘密荘厳心（真言密教の心） 顕教の教えは、宝の箱の塵を払うような効用しかあり",
          "context_position": 5784,
          "sanskrit_in_context": []
        },
        {
          "corpus_id": "hizo-houyaku",
          "context": "） 顕教の教えは、宝の箱の塵を払うような効用しかありません。真言密教こそ宝の庫を開き、中の秘宝が陳げられて、如来の徳をこの身",
          "context_position": 5820,
          "sanskrit_in_context": []
        },
        {
          "corpus_id": "hizo-houyaku",
          "context": "楽にすることだけにつとめ、三毒とか五慾に身をまかせています。真言行人は、まことにこれを厭い患えなければなりません。まことにこ",
          "context_position": 9370,
          "sanskrit_in_context": []
        },
        {
          "corpus_id": "hizo-houyaku",
          "context": "と。また同じくこうも言っています。 「もし諸天・世間の中にも真言法教の道が見えるのは、勤勇者が衆生を利益しようとするためであ",
          "context_position": 18519,
          "sanskrit_in_context": []
        },
        {
          "corpus_id": "hizo-houyaku",
          "context": "いはまた彼らは天に生まれることを最高の目的と思っています。 真言行を修している人たちは彼らを見てこう思いなさい。あの修行の業",
          "context_position": 18656,
          "sanskrit_in_context": []
        },
        {
          "corpus_id": "hizo-houyaku",
          "context": "す」と。 また同経具縁品にこう言っています、「もし声聞の説く真言の場合には、密教のように一言のうちに多義を含めることができな",
          "context_position": 22556,
          "sanskrit_in_context": []
        },
        {
          "corpus_id": "hizo-houyaku",
          "context": "です。すなわち、一仏の名号を称えれば無量の重罪が消え、一字の真言を讃すれば無辺の功徳が得られるのです。まして、僧侶が国から受",
          "context_position": 30800,
          "sanskrit_in_context": []
        },
        {
          "corpus_id": "hizo-houyaku",
          "context": "ために（御自分の法楽のために）説かれた教えなのです。いわゆる真言乗（真言密教）がこれです。 これら三種類の教えは、人々の能力",
          "context_position": 33381,
          "sanskrit_in_context": []
        },
        {
          "corpus_id": "hizo-houyaku",
          "context": "御自分の法楽のために）説かれた教えなのです。いわゆる真言乗（真言密教）がこれです。 これら三種類の教えは、人々の能力に応じて",
          "context_position": 33385,
          "sanskrit_in_context": []
        },
        {
          "corpus_id": "hizo-houyaku",
          "context": "にこうも言っています、「秘密主よ、もし縁覚や声聞の説いている真言の教えに住していれば、諸の過患をくだき害ることができます」と",
          "context_position": 43401,
          "sanskrit_in_context": []
        },
        {
          "corpus_id": "hizo-houyaku",
          "context": "。 また同じく具縁品にこうも言っています、「声聞の人々の説く真言は、一つ一つの句が並べられていますが、辟支仏（縁覚）の場合は",
          "context_position": 43463,
          "sanskrit_in_context": []
        },
        {
          "corpus_id": "hizo-houyaku",
          "context": "行して、縁覚の悟りに至り、これを究極のものと考えています。 真言行者は次のように考えるべきです、声聞・縁覚等の南方仏教の人々",
          "context_position": 43731,
          "sanskrit_in_context": []
        },
        {
          "corpus_id": "hizo-houyaku",
          "context": "価値を法相・三論・天台・華厳に順に配し、第五の不二摩訶衍こそ真言密教を意味するのだと理解した。不二摩訶衍が本来なにを意味する",
          "context_position": 49272,
          "sanskrit_in_context": []
        },
        {
          "corpus_id": "hizo-houyaku",
          "context": "不滅という本性なのだと覚ること、これこそ阿字門に入り、次第に真言の悟りに近づいていくことなのです。 こうした無為の生死（悟っ",
          "context_position": 51946,
          "sanskrit_in_context": []
        },
        {
          "corpus_id": "hizo-houyaku",
          "context": "こで仏道といっているのは、金剛法界宮の大曼荼羅の仏、すなわち真言密教の中心の仏を指すのです。諸の顕教においては、これを「究竟",
          "context_position": 58099,
          "sanskrit_in_context": []
        },
        {
          "corpus_id": "hizo-houyaku",
          "context": "においては、これを「究竟の理智法身」と名づけているのですが、真言密教の教えと比べてみれば、こうした考えはまだ入口にすぎません",
          "context_position": 58149,
          "sanskrit_in_context": []
        },
        {
          "corpus_id": "hizo-houyaku",
          "context": "地（自分の心を観察する気持に専念すること）に住して自性成就の真言をもって自ら自由に念誦しなさい〉」と。 ◇ 『守護国界主陀羅",
          "context_position": 65457,
          "sanskrit_in_context": []
        },
        {
          "corpus_id": "hizo-houyaku",
          "context": "めます。 九種の住心は自性無し 転深転妙にして皆これ因なり 真言密教は法身の説 秘密金剛は最勝の真なり （これまでの九種の住",
          "context_position": 67542,
          "sanskrit_in_context": []
        },
        {
          "corpus_id": "hizo-houyaku",
          "context": "各々が次の住心の因となっているのです。 しかしこの第十住心の真言密教は、法身大日如来の説であり、秘密金剛の教えで、最もすぐれ",
          "context_position": 67649,
          "sanskrit_in_context": []
        },
        {
          "corpus_id": "hizo-houyaku",
          "context": "拠 『大日経』住心品にこう言っています、「また次に秘密主よ。真言密教において菩薩の修行をするすべての菩薩は、無量無数百千億劫",
          "context_position": 68050,
          "sanskrit_in_context": []
        },
        {
          "corpus_id": "hizo-houyaku",
          "context": "とができるのです」と。 これを釈しますと、この一段は、初めて真言門に入る菩薩の功徳を讃歎しているという意味であります。 また",
          "context_position": 68186,
          "sanskrit_in_context": []
        },
        {
          "corpus_id": "hizo-houyaku",
          "context": "しいのです。また、この『大日経』には、百字輪とか十二字などの真言の観法や三摩地法門があり、また『金剛頂経』にも、金剛界三十七",
          "context_position": 68512,
          "sanskrit_in_context": []
        },
        {
          "corpus_id": "hizo-houyaku",
          "context": "論』にこう言っています。 「第三に三摩地の菩提心というのは、真言行人がこのように観察しおわって、どのようにして無上菩提を証す",
          "context_position": 68897,
          "sanskrit_in_context": []
        },
        {
          "corpus_id": "hizo-houyaku",
          "context": "すと、まさに一切智を具すことになるのです。 五相成身観 凡そ真言の瑜伽の観行を修習する人は、まさに三密の行を修し、五相成身の",
          "context_position": 71543,
          "sanskrit_in_context": []
        },
        {
          "corpus_id": "hizo-houyaku",
          "context": "するなどのことがこれです。二には語密であり、行者がひそやかに真言（陀羅尼、秘密語）を誦してその真言の文句を心に観じてよくはっ",
          "context_position": 71661,
          "sanskrit_in_context": []
        },
        {
          "corpus_id": "hizo-houyaku",
          "context": "密であり、行者がひそやかに真言（陀羅尼、秘密語）を誦してその真言の文句を心に観じてよくはっきりと理解し、間違いなく唱えるなど",
          "context_position": 71678,
          "sanskrit_in_context": []
        },
        {
          "corpus_id": "hizo-houyaku",
          "context": "きで、決して頼りにすべきものではありません。 これに比べて、真言行人（真言密教の修行者）は、すでに人執と法執の二つの執着を破",
          "context_position": 72592,
          "sanskrit_in_context": []
        },
        {
          "corpus_id": "hizo-houyaku",
          "context": "て頼りにすべきものではありません。 これに比べて、真言行人（真言密教の修行者）は、すでに人執と法執の二つの執着を破しています",
          "context_position": 72597,
          "sanskrit_in_context": []
        },
        {
          "corpus_id": "hizo-houyaku",
          "context": "からこの心地をさずけられてしかる後によく証果す〉と。 およそ真言の行人ならば、もし心が決定して教えのごとく修行すれば、その座",
          "context_position": 73019,
          "sanskrit_in_context": []
        },
        {
          "corpus_id": "hizo-houyaku",
          "context": "の頌を聴きましたが、どうかその意味を説明して下さい。 答う、真言密教では、一一の声字にも、一一の言名にも、一一の句義・一一の",
          "context_position": 73569,
          "sanskrit_in_context": []
        },
        {
          "corpus_id": "hizo-houyaku",
          "context": "す。また一一の句にも浅略釈と深秘釈（一般仏教の解釈を浅略釈、真言密教の解釈を深秘釈という）との二義がありますから、簡単におは",
          "context_position": 73769,
          "sanskrit_in_context": []
        },
        {
          "corpus_id": "hizo-houyaku",
          "context": "といえども説いてはなりません。もし本尊の儀軌（お経のこと）や真言などの場合は、たとえ同じ教えの仲間であってもたやすく説いては",
          "context_position": 74170,
          "sanskrit_in_context": []
        },
        {
          "corpus_id": "hizo-houyaku",
          "context": "いて、死んだ後には無間地獄に堕ちるのです。云云」と。 問う、真言の教法はたやすく説くべきでないというご注意はつつしんで承わり",
          "context_position": 74270,
          "sanskrit_in_context": []
        },
        {
          "corpus_id": "hizo-houyaku",
          "context": "々深妙だからこのゆえに「深妙」と言うのです。 次に第三句の「真言密教は法身の説」とはこの一句は真言密教の教主をあらわしていま",
          "context_position": 74923,
          "sanskrit_in_context": []
        },
        {
          "corpus_id": "hizo-houyaku",
          "context": "うのです。 次に第三句の「真言密教は法身の説」とはこの一句は真言密教の教主をあらわしています。極無自性以下の教えはみな、他受",
          "context_position": 74940,
          "sanskrit_in_context": []
        },
        {
          "corpus_id": "hizo-houyaku",
          "context": "教えはみな、他受用身または変化身の仏の所説であります。そして真言密教の金剛界と胎蔵法（界）という二つの秘蔵（秘密の蔵で真言密",
          "context_position": 74994,
          "sanskrit_in_context": []
        },
        {
          "corpus_id": "hizo-houyaku",
          "context": "て真言密教の金剛界と胎蔵法（界）という二つの秘蔵（秘密の蔵で真言密教を指す）は、これだけが、法身大日如来のお説きになった教え",
          "context_position": 75023,
          "sanskrit_in_context": []
        },
        {
          "corpus_id": "hizo-houyaku",
          "context": "、自分の眷族である四種法身の仏・菩薩と共に、金剛法界宮および真言宮殿等に住して、自受法楽のゆえに演説された教えなのです。『十",
          "context_position": 75097,
          "sanskrit_in_context": []
        },
        {
          "corpus_id": "hizo-houyaku",
          "context": "も不要なほどです。 第四句の「秘密金剛は最勝の真なり」とは、真言乗の教えが、諸の他の教えを越えて、究極の真実であることを示し",
          "context_position": 75205,
          "sanskrit_in_context": []
        }
      ]
    },
    {
      "term": "密教",
      "term_kana": "",
      "sanskrit": "guhya-mantra-yāna",
      "definition": "空海の宗派自称。秘密真言乗。大日如来の内証を直接伝える教え。",
      "kaimyo_suitable": false,
      "kaimyo_chars": [],
      "occurrence_count": 36,
      "occurrences": [
        {
          "corpus_id": "hizo-houyaku",
          "context": "心に本来具わっていた曼荼羅の荘厳がようやく開くのです。 さて密教の世界に入るには、まず良き師に出遭い、その教えを深く信受して",
          "context_position": 2635,
          "sanskrit_in_context": []
        },
        {
          "corpus_id": "hizo-houyaku",
          "context": "てられ、新しく目を見開くと、ここに自分自身が金剛薩埵、つまり密教の正統の後継者であることを自覚するのです。 密教の世界では、",
          "context_position": 2793,
          "sanskrit_in_context": []
        },
        {
          "corpus_id": "hizo-houyaku",
          "context": "薩埵、つまり密教の正統の後継者であることを自覚するのです。 密教の世界では、金剛界のすべての諸尊は五部にわかれて居並び、それ",
          "context_position": 2817,
          "sanskrit_in_context": []
        },
        {
          "corpus_id": "hizo-houyaku",
          "context": "という禅定女たちは、適悦という微妙な法楽を受けるのです。この密教の境地は、仏陀の心の奥底の境界ですから、他の教えのいかなるす",
          "context_position": 3122,
          "sanskrit_in_context": []
        },
        {
          "corpus_id": "hizo-houyaku",
          "context": "、どのように高度な者でも、列席することはできないのです。この密教の境地は、秘密の中の秘密であり、覚りの中の覚りというべきもの",
          "context_position": 3191,
          "sanskrit_in_context": []
        },
        {
          "corpus_id": "hizo-houyaku",
          "context": "過しているならば、如来は必ずこれをお叱りになります。つまり、密教以外の九種の教え（これを顕教という）は、宮殿の外側の塵を払っ",
          "context_position": 3486,
          "sanskrit_in_context": []
        },
        {
          "corpus_id": "hizo-houyaku",
          "context": "顕教という）は、宮殿の外側の塵を払っているようなもので、真言密教こそが、宝の宮殿の鍵をあけて、中の宝物を手に入れることができ",
          "context_position": 3530,
          "sanskrit_in_context": []
        },
        {
          "corpus_id": "hizo-houyaku",
          "context": "を受けてさらに次に進んで行くのです。 第十、秘密荘厳心（真言密教の心） 顕教の教えは、宝の箱の塵を払うような効用しかありませ",
          "context_position": 5786,
          "sanskrit_in_context": []
        },
        {
          "corpus_id": "hizo-houyaku",
          "context": "顕教の教えは、宝の箱の塵を払うような効用しかありません。真言密教こそ宝の庫を開き、中の秘宝が陳げられて、如来の徳をこの身に体",
          "context_position": 5822,
          "sanskrit_in_context": []
        },
        {
          "corpus_id": "hizo-houyaku",
          "context": "事をよく処理することです（不乱は一般仏教では不飲酒に当るが、密教では不飲酒に替えて不邪見を用いている。訳者注）。信とは不妄語",
          "context_position": 10784,
          "sanskrit_in_context": []
        },
        {
          "corpus_id": "hizo-houyaku",
          "context": "ますから、これによって得られる利益となると全く別であります。密教でいえばこの住心は、悪を断じ善を修する最初の出発点であり、世",
          "context_position": 11159,
          "sanskrit_in_context": []
        },
        {
          "corpus_id": "hizo-houyaku",
          "context": "経具縁品にこう言っています、「もし声聞の説く真言の場合には、密教のように一言のうちに多義を含めることができないから、一つ一つ",
          "context_position": 22564,
          "sanskrit_in_context": []
        },
        {
          "corpus_id": "hizo-houyaku",
          "context": "大きく分けて二種類あります。一つには顕教の法であり、二つには密教の法です。この顕教の中にまた二つあります。一乗の教えと三乗の",
          "context_position": 32977,
          "sanskrit_in_context": []
        },
        {
          "corpus_id": "hizo-houyaku",
          "context": "、四十一位を初地、五十位を第十地という。 ◇ これらに対して密教とは、自性法身である大日如来がお説きになった教えです。この如",
          "context_position": 33300,
          "sanskrit_in_context": []
        },
        {
          "corpus_id": "hizo-houyaku",
          "context": "分の法楽のために）説かれた教えなのです。いわゆる真言乗（真言密教）がこれです。 これら三種類の教えは、人々の能力に応じて如来",
          "context_position": 33387,
          "sanskrit_in_context": []
        },
        {
          "corpus_id": "hizo-houyaku",
          "context": "を法相・三論・天台・華厳に順に配し、第五の不二摩訶衍こそ真言密教を意味するのだと理解した。不二摩訶衍が本来なにを意味するのか",
          "context_position": 49274,
          "sanskrit_in_context": []
        },
        {
          "corpus_id": "hizo-houyaku",
          "context": "不可得だからです。このように自分の心の本性を知ること、これが密教でいえば第二劫を超越する瑜祇行（密教の修行）なのです」と。 ",
          "context_position": 52775,
          "sanskrit_in_context": []
        },
        {
          "corpus_id": "hizo-houyaku",
          "context": "の本性を知ること、これが密教でいえば第二劫を超越する瑜祇行（密教の修行）なのです」と。 また『菩提心論』にはこう言っています",
          "context_position": 52793,
          "sanskrit_in_context": []
        },
        {
          "corpus_id": "hizo-houyaku",
          "context": "仏道といっているのは、金剛法界宮の大曼荼羅の仏、すなわち真言密教の中心の仏を指すのです。諸の顕教においては、これを「究竟の理",
          "context_position": 58101,
          "sanskrit_in_context": []
        },
        {
          "corpus_id": "hizo-houyaku",
          "context": "いては、これを「究竟の理智法身」と名づけているのですが、真言密教の教えと比べてみれば、こうした考えはまだ入口にすぎません。『",
          "context_position": 58151,
          "sanskrit_in_context": []
        },
        {
          "corpus_id": "hizo-houyaku",
          "context": "手菩薩、金剛手秘密主、秘密主、金剛手、これらは皆同じ菩薩で、密教では大日如来の教えを承ける菩薩として重要な役目を持っている。",
          "context_position": 58716,
          "sanskrit_in_context": []
        },
        {
          "corpus_id": "hizo-houyaku",
          "context": "のは一智ですべて一切を知ることができる、ということであるが、密教で大日如来は、マンダラ上で四仏にとりかこまれて五仏となり、同",
          "context_position": 58795,
          "sanskrit_in_context": []
        },
        {
          "corpus_id": "hizo-houyaku",
          "context": "かし、この宮殿に達したとしても、それはまだ初発の仏であって、密教の五相成身観をさらに追いたずねなければならないのです。 ＊十",
          "context_position": 64659,
          "sanskrit_in_context": []
        },
        {
          "corpus_id": "hizo-houyaku",
          "context": "す。 九種の住心は自性無し 転深転妙にして皆これ因なり 真言密教は法身の説 秘密金剛は最勝の真なり （これまでの九種の住心は",
          "context_position": 67544,
          "sanskrit_in_context": []
        },
        {
          "corpus_id": "hizo-houyaku",
          "context": "が次の住心の因となっているのです。 しかしこの第十住心の真言密教は、法身大日如来の説であり、秘密金剛の教えで、最もすぐれた真",
          "context_position": 67651,
          "sanskrit_in_context": []
        },
        {
          "corpus_id": "hizo-houyaku",
          "context": "『大日経』住心品にこう言っています、「また次に秘密主よ。真言密教において菩薩の修行をするすべての菩薩は、無量無数百千億劫とい",
          "context_position": 68052,
          "sanskrit_in_context": []
        },
        {
          "corpus_id": "hizo-houyaku",
          "context": "りにすべきものではありません。 これに比べて、真言行人（真言密教の修行者）は、すでに人執と法執の二つの執着を破しています。真",
          "context_position": 72599,
          "sanskrit_in_context": []
        },
        {
          "corpus_id": "hizo-houyaku",
          "context": "を聴きましたが、どうかその意味を説明して下さい。 答う、真言密教では、一一の声字にも、一一の言名にも、一一の句義・一一の文章",
          "context_position": 73571,
          "sanskrit_in_context": []
        },
        {
          "corpus_id": "hizo-houyaku",
          "context": "また一一の句にも浅略釈と深秘釈（一般仏教の解釈を浅略釈、真言密教の解釈を深秘釈という）との二義がありますから、簡単におはなし",
          "context_position": 73771,
          "sanskrit_in_context": []
        },
        {
          "corpus_id": "hizo-houyaku",
          "context": "を応化の仏身という）の身となられて出世された釈尊も、黙して、密教をあえて説かれなかったのであり、教法を伝える菩薩たちも、その",
          "context_position": 74006,
          "sanskrit_in_context": []
        },
        {
          "corpus_id": "hizo-houyaku",
          "context": "かったのであり、教法を伝える菩薩たちも、そのままにしてあえて密教を論じませんでしたのも、みな誤解を避けたためでありましょう。",
          "context_position": 74046,
          "sanskrit_in_context": []
        },
        {
          "corpus_id": "hizo-houyaku",
          "context": "妙だからこのゆえに「深妙」と言うのです。 次に第三句の「真言密教は法身の説」とはこの一句は真言密教の教主をあらわしています。",
          "context_position": 74925,
          "sanskrit_in_context": []
        },
        {
          "corpus_id": "hizo-houyaku",
          "context": "です。 次に第三句の「真言密教は法身の説」とはこの一句は真言密教の教主をあらわしています。極無自性以下の教えはみな、他受用身",
          "context_position": 74942,
          "sanskrit_in_context": []
        },
        {
          "corpus_id": "hizo-houyaku",
          "context": "はみな、他受用身または変化身の仏の所説であります。そして真言密教の金剛界と胎蔵法（界）という二つの秘蔵（秘密の蔵で真言密教を",
          "context_position": 74996,
          "sanskrit_in_context": []
        },
        {
          "corpus_id": "hizo-houyaku",
          "context": "言密教の金剛界と胎蔵法（界）という二つの秘蔵（秘密の蔵で真言密教を指す）は、これだけが、法身大日如来のお説きになった教えなの",
          "context_position": 75025,
          "sanskrit_in_context": []
        },
        {
          "corpus_id": "hizo-houyaku",
          "context": "法楽のゆえに演説された教えなのです。『十八会指帰』（不空訳の密教経典）等にそのいきさつが明らかにされていまして、それ以上のな",
          "context_position": 75139,
          "sanskrit_in_context": []
        }
      ]
    },
    {
      "term": "法界",
      "term_kana": "",
      "sanskrit": "dharma-dhātu",
      "definition": "宇宙の真実相。一切法の根本領域。",
      "kaimyo_suitable": true,
      "kaimyo_chars": [
        "法",
        "界"
      ],
      "occurrence_count": 25,
      "occurrences": [
        {
          "corpus_id": "hizo-houyaku",
          "context": "。 次に華厳の教学を修めて、華厳宗の悟りの世界である事事無碍法界〔＊〕を観じ、初発心すれば直ちに究極の悟りに達するというよう",
          "context_position": 2382,
          "sanskrit_in_context": []
        },
        {
          "corpus_id": "hizo-houyaku",
          "context": "笑してその境地を承認したもうのです（第九住心）。 ＊事事無碍法界……現象界は互いに作用し合い交渉し合って、一と多が無尽に縁起",
          "context_position": 2472,
          "sanskrit_in_context": []
        },
        {
          "corpus_id": "hizo-houyaku",
          "context": "りの有であり、同時に他の一面に於ては空であり、これがそのまま法界の相である、と観察すれば、そこに縁起による中道〔＊〕の正しい",
          "context_position": 16537,
          "sanskrit_in_context": []
        },
        {
          "corpus_id": "hizo-houyaku",
          "context": "の世界では、「一真」という楼台に昇ってゆったりと手を組み、「法界」という御殿に住んで泰らかに過ごすのです。 三大阿僧祇という",
          "context_position": 46249,
          "sanskrit_in_context": []
        },
        {
          "corpus_id": "hizo-houyaku",
          "context": "異るがいずれもまことに壮大な仏国土である。 第六住心の名前 法界のすべての生きとし生けるものを教化の対象とする住心ですから「",
          "context_position": 47306,
          "sanskrit_in_context": []
        },
        {
          "corpus_id": "hizo-houyaku",
          "context": "真如の理はことばにもあらわせず心でもとらえられないのですが、法界には遍満しているのです。これを知らずに生死の海に浮き沈み、も",
          "context_position": 48067,
          "sanskrit_in_context": []
        },
        {
          "corpus_id": "hizo-houyaku",
          "context": "道の初門」と名づけています。ここで仏道といっているのは、金剛法界宮の大曼荼羅の仏、すなわち真言密教の中心の仏を指すのです。諸",
          "context_position": 58084,
          "sanskrit_in_context": []
        },
        {
          "corpus_id": "hizo-houyaku",
          "context": "身）なのです。当然に法身ではありません。 問う、このような一法界の道理、一道真如の真理は、究竟の仏というべきでしょうか。 答",
          "context_position": 59599,
          "sanskrit_in_context": []
        },
        {
          "corpus_id": "hizo-houyaku",
          "context": "、『釈摩訶衍論』で竜猛菩薩は次のように説いています、「この一法界の心は、あらゆる否定によっても表現できないし、あらゆる肯定に",
          "context_position": 59662,
          "sanskrit_in_context": []
        },
        {
          "corpus_id": "hizo-houyaku",
          "context": "てくる巧歴のような、すぐれた暦法の達人でも、また『華厳経』入法界品に出てくる衆芸覚童子のような算術の達人でも、「心の仏」に向",
          "context_position": 60399,
          "sanskrit_in_context": []
        },
        {
          "corpus_id": "hizo-houyaku",
          "context": "立ってながめると、華蔵世界の全体を自分の家とみており、一切の法界を包み込んでこれを自分の国土と考えているのです。またこの経は",
          "context_position": 62041,
          "sanskrit_in_context": []
        },
        {
          "corpus_id": "hizo-houyaku",
          "context": "る世界がこの華厳の悟りの世界なのです。 さらにまた最後の「入法界品」においては、善財童子の求道の物語が説かれています。すなわ",
          "context_position": 63121,
          "sanskrit_in_context": []
        },
        {
          "corpus_id": "hizo-houyaku",
          "context": "ば『華厳経』の大意は、その始めを原ね終りを要めますと、〈真如法界は自性を守らず、因縁に随う（常に変化している）〉という意味を",
          "context_position": 63835,
          "sanskrit_in_context": []
        },
        {
          "corpus_id": "hizo-houyaku",
          "context": "（西暦六四〇年寂）がこの法門を研究し、『華厳五教止観』『華厳法界観』などを著作され、その弟子の智儼師はこれを承けて弘め、その",
          "context_position": 63945,
          "sanskrit_in_context": []
        },
        {
          "corpus_id": "hizo-houyaku",
          "context": "ころにしている、といいます。 この対照的な二人の竜王が結局一法界であり一つのものであるように、真如門（変らない世界）と生滅門",
          "context_position": 64187,
          "sanskrit_in_context": []
        },
        {
          "corpus_id": "hizo-houyaku",
          "context": "に、真如門（変らない世界）と生滅門（揺れ動く世界）とはこの一法界の峯に帰一するのです。 また『釈摩訶衍論』巻三に出ている輪多",
          "context_position": 64232,
          "sanskrit_in_context": []
        },
        {
          "corpus_id": "hizo-houyaku",
          "context": "とが互いに一体化してさまたげない縁起の様子をあらわしている。法界縁起がこれである。 第九住心の典拠（二） 『大日経』の住心品",
          "context_position": 64770,
          "sanskrit_in_context": []
        },
        {
          "corpus_id": "hizo-houyaku",
          "context": "ぐれた真実の生きかたです） その教えは、五相成身観と五智と、法界体性と、四種曼荼羅と四智印等であって、この住心の中に陳べられ",
          "context_position": 67709,
          "sanskrit_in_context": []
        },
        {
          "corpus_id": "hizo-houyaku",
          "context": "世尊は、一切如来一体速疾力三昧という禅定に入って、自ら悟った法界体性三昧を説いて言いました。〈我本不生を覚り、語言の道を出過",
          "context_position": 68279,
          "sanskrit_in_context": []
        },
        {
          "corpus_id": "hizo-houyaku",
          "context": "えた境地を〈無覚了〉（覚るべき何物もないという境地）とも〈浄法界〉（清らかなる仏の世界）とも名づけます。あるいはまた〈実相般",
          "context_position": 69318,
          "sanskrit_in_context": []
        },
        {
          "corpus_id": "hizo-houyaku",
          "context": "えに、羯磨智と名づけるのです。中央の大日如来・毘盧遮那仏は、法界体性智を成ずるに由るもので、これを根本智といいます。四方の四",
          "context_position": 69897,
          "sanskrit_in_context": []
        },
        {
          "corpus_id": "hizo-houyaku",
          "context": "一切の諸賢聖を生み出し養育する母体です。ここにおいて印成する法界体性の中に四仏を出生するのです。 四方の如来にも各々四菩薩が",
          "context_position": 70004,
          "sanskrit_in_context": []
        },
        {
          "corpus_id": "hizo-houyaku",
          "context": "もしこの観智が次第に増ます増大してきますと、それがひろびろと法界に周ねく広がり、その量は虚空と等しくなります。そして巻くも舒",
          "context_position": 71470,
          "sanskrit_in_context": []
        },
        {
          "corpus_id": "hizo-houyaku",
          "context": "の三摩地というのは、よく諸仏の自性に達し、諸仏の法身を覚り、法界体性智を証すること、そして大毘盧遮那仏の自性身・受用身・変化",
          "context_position": 72769,
          "sanskrit_in_context": []
        },
        {
          "corpus_id": "hizo-houyaku",
          "context": "の大日如来が、自分の眷族である四種法身の仏・菩薩と共に、金剛法界宮および真言宮殿等に住して、自受法楽のゆえに演説された教えな",
          "context_position": 75091,
          "sanskrit_in_context": []
        }
      ]
    },
    {
      "term": "法身",
      "term_kana": "",
      "sanskrit": "dharmakāya",
      "definition": "仏の真実身。大日如来は六大法身。形相を超えた法そのもの。",
      "kaimyo_suitable": true,
      "kaimyo_chars": [
        "法",
        "身"
      ],
      "occurrence_count": 25,
      "occurrences": [
        {
          "corpus_id": "hizo-houyaku",
          "context": "地、五十位を第十地という。 ◇ これらに対して密教とは、自性法身である大日如来がお説きになった教えです。この如来が御自分の眷",
          "context_position": 33307,
          "sanskrit_in_context": []
        },
        {
          "corpus_id": "hizo-houyaku",
          "context": "の成果が手に入るのです。ここには常・楽・我・浄という四徳と、法身・般若・解脱という三点の徳〔＊〕とを自分の身に具えることがで",
          "context_position": 47957,
          "sanskrit_in_context": []
        },
        {
          "corpus_id": "hizo-houyaku",
          "context": "から三つの大切なものを表わして伊字の三点という。涅槃経で説く法身・般若・解脱もその一種。法身は如来の身、般若は如来の智慧、解",
          "context_position": 48181,
          "sanskrit_in_context": []
        },
        {
          "corpus_id": "hizo-houyaku",
          "context": "て伊字の三点という。涅槃経で説く法身・般若・解脱もその一種。法身は如来の身、般若は如来の智慧、解脱はあらゆる束縛から解放され",
          "context_position": 48195,
          "sanskrit_in_context": []
        },
        {
          "corpus_id": "hizo-houyaku",
          "context": "の相〉といい〈青に非ず黄に非ず〉等というのは、いずれもこれは法身真如の一道無畏（第八住心）の真理を明かしているので、仏はこれ",
          "context_position": 57984,
          "sanskrit_in_context": []
        },
        {
          "corpus_id": "hizo-houyaku",
          "context": "中心の仏を指すのです。諸の顕教においては、これを「究竟の理智法身」と名づけているのですが、真言密教の教えと比べてみれば、こう",
          "context_position": 58134,
          "sanskrit_in_context": []
        },
        {
          "corpus_id": "hizo-houyaku",
          "context": "を離れ、眼・耳・鼻・舌・身・意を離れています」と。この文は理法身〔＊〕を明かしたものです。 『大日経疏』ではさらにこう言いま",
          "context_position": 58386,
          "sanskrit_in_context": []
        },
        {
          "corpus_id": "hizo-houyaku",
          "context": "の道理を証する仏を〈浄寂光土の毘盧遮那仏〉と名づけるのです。法身大毘盧遮那仏ではないのです。 ＊金剛手菩薩（秘密主）……金剛",
          "context_position": 58654,
          "sanskrit_in_context": []
        },
        {
          "corpus_id": "hizo-houyaku",
          "context": "切智智という。マンダラを頭に置いて理解する必要がある。 ＊理法身……法身を理論的な面と実体的な面に分けて考える方法。理法身は",
          "context_position": 58957,
          "sanskrit_in_context": []
        },
        {
          "corpus_id": "hizo-houyaku",
          "context": "いう。マンダラを頭に置いて理解する必要がある。 ＊理法身……法身を理論的な面と実体的な面に分けて考える方法。理法身は、法身を",
          "context_position": 58961,
          "sanskrit_in_context": []
        },
        {
          "corpus_id": "hizo-houyaku",
          "context": "理法身……法身を理論的な面と実体的な面に分けて考える方法。理法身は、法身を理論的な考えでとらえる探究方法。他方で智法身は、法",
          "context_position": 58986,
          "sanskrit_in_context": []
        },
        {
          "corpus_id": "hizo-houyaku",
          "context": "…法身を理論的な面と実体的な面に分けて考える方法。理法身は、法身を理論的な考えでとらえる探究方法。他方で智法身は、法身を人格",
          "context_position": 58990,
          "sanskrit_in_context": []
        },
        {
          "corpus_id": "hizo-houyaku",
          "context": "法。理法身は、法身を理論的な考えでとらえる探究方法。他方で智法身は、法身を人格的にとらえようとする考え方による。空海上人は、",
          "context_position": 59013,
          "sanskrit_in_context": []
        },
        {
          "corpus_id": "hizo-houyaku",
          "context": "身は、法身を理論的な考えでとらえる探究方法。他方で智法身は、法身を人格的にとらえようとする考え方による。空海上人は、大日如来",
          "context_position": 59017,
          "sanskrit_in_context": []
        },
        {
          "corpus_id": "hizo-houyaku",
          "context": "的にとらえようとする考え方による。空海上人は、大日如来を理智法身の境界と言っている。 第八住心の主張者 隋の天台山国清寺の智",
          "context_position": 59052,
          "sanskrit_in_context": []
        },
        {
          "corpus_id": "hizo-houyaku",
          "context": "て下さる変化身（いろいろにお姿を変えた仏身）なのです。当然に法身ではありません。 問う、このような一法界の道理、一道真如の真",
          "context_position": 59579,
          "sanskrit_in_context": []
        },
        {
          "corpus_id": "hizo-houyaku",
          "context": "性があるわけではありません。 また次に、諸仏の大慈悲は、真如法身からはたらきを起こして衆生を救って下さるのです。病に応じて薬",
          "context_position": 66392,
          "sanskrit_in_context": []
        },
        {
          "corpus_id": "hizo-houyaku",
          "context": "習（影響を与え指導）して一覚（一まとめのさとり）となし、一大法身の果（仏陀の法身）を荘厳するのです。このゆえに名づけて〈因薫",
          "context_position": 66744,
          "sanskrit_in_context": []
        },
        {
          "corpus_id": "hizo-houyaku",
          "context": "導）して一覚（一まとめのさとり）となし、一大法身の果（仏陀の法身）を荘厳するのです。このゆえに名づけて〈因薫習鏡〉というので",
          "context_position": 66752,
          "sanskrit_in_context": []
        },
        {
          "corpus_id": "hizo-houyaku",
          "context": "九種の住心は自性無し 転深転妙にして皆これ因なり 真言密教は法身の説 秘密金剛は最勝の真なり （これまでの九種の住心は、次々",
          "context_position": 67547,
          "sanskrit_in_context": []
        },
        {
          "corpus_id": "hizo-houyaku",
          "context": "心の因となっているのです。 しかしこの第十住心の真言密教は、法身大日如来の説であり、秘密金剛の教えで、最もすぐれた真実の生き",
          "context_position": 67655,
          "sanskrit_in_context": []
        },
        {
          "corpus_id": "hizo-houyaku",
          "context": " すなわちこの三摩地というのは、よく諸仏の自性に達し、諸仏の法身を覚り、法界体性智を証すること、そして大毘盧遮那仏の自性身・",
          "context_position": 72763,
          "sanskrit_in_context": []
        },
        {
          "corpus_id": "hizo-houyaku",
          "context": "らこのゆえに「深妙」と言うのです。 次に第三句の「真言密教は法身の説」とはこの一句は真言密教の教主をあらわしています。極無自",
          "context_position": 74928,
          "sanskrit_in_context": []
        },
        {
          "corpus_id": "hizo-houyaku",
          "context": "という二つの秘蔵（秘密の蔵で真言密教を指す）は、これだけが、法身大日如来のお説きになった教えなのです。この大日如来が、自分の",
          "context_position": 75039,
          "sanskrit_in_context": []
        },
        {
          "corpus_id": "hizo-houyaku",
          "context": "きになった教えなのです。この大日如来が、自分の眷族である四種法身の仏・菩薩と共に、金剛法界宮および真言宮殿等に住して、自受法",
          "context_position": 75078,
          "sanskrit_in_context": []
        }
      ]
    },
    {
      "term": "遮那",
      "term_kana": "",
      "sanskrit": "Vairocana",
      "definition": "毘盧遮那の略。大日如来。光明遍照。",
      "kaimyo_suitable": true,
      "kaimyo_chars": [
        "遮",
        "那"
      ],
      "occurrence_count": 16,
      "occurrences": [
        {
          "corpus_id": "hizo-houyaku",
          "context": "になっています。この受け止めかたを知っているのは、顕教の毘盧遮那仏です。 第九、極無自性心（華厳宗の心） 華厳宗の教理による",
          "context_position": 5613,
          "sanskrit_in_context": []
        },
        {
          "corpus_id": "hizo-houyaku",
          "context": "けるだけのことです」と。この道理を証する仏を〈浄寂光土の毘盧遮那仏〉と名づけるのです。法身大毘盧遮那仏ではないのです。 ＊金",
          "context_position": 58641,
          "sanskrit_in_context": []
        },
        {
          "corpus_id": "hizo-houyaku",
          "context": "する仏を〈浄寂光土の毘盧遮那仏〉と名づけるのです。法身大毘盧遮那仏ではないのです。 ＊金剛手菩薩（秘密主）……金剛手菩薩、金",
          "context_position": 58659,
          "sanskrit_in_context": []
        },
        {
          "corpus_id": "hizo-houyaku",
          "context": "光の仏土であり、この住心の仏は、言語による表現のできない毘盧遮那仏です。その仏は、身・心ともに滅して虚空と等同なのですが、応",
          "context_position": 59470,
          "sanskrit_in_context": []
        },
        {
          "corpus_id": "hizo-houyaku",
          "context": "ややあらわれてきます。 華厳宗の宇宙観によれば、全宇宙を毘盧遮那仏の顕現であると考えます。そしてこれを「三種世間を融会した十",
          "context_position": 61720,
          "sanskrit_in_context": []
        },
        {
          "corpus_id": "hizo-houyaku",
          "context": "意 次に『華厳経』によってこの教えの大意を述べましょう。毘盧遮那仏は、はじめて菩提樹下に成道された時に、その第二・七日（第二",
          "context_position": 61909,
          "sanskrit_in_context": []
        },
        {
          "corpus_id": "hizo-houyaku",
          "context": "いるから）また華厳宗によれば、『華厳経』の内容はすべて、毘盧遮那仏が海印定（天上のものが七海の上にあらわれるようにこの定に入",
          "context_position": 62157,
          "sanskrit_in_context": []
        },
        {
          "corpus_id": "hizo-houyaku",
          "context": "らし、次第に低い山や平地を照していきます。それと同様に、毘盧遮那仏が悟られて『華厳経』を説かれた時も、まずはじめに山の頂きに",
          "context_position": 62350,
          "sanskrit_in_context": []
        },
        {
          "corpus_id": "hizo-houyaku",
          "context": "四千の法門のためのひかりであり、錠前なのです。唵字はこれ毘盧遮那の真身です。唵字はこれ、一切の陀羅尼の母なのです。一切の如来",
          "context_position": 66109,
          "sanskrit_in_context": []
        },
        {
          "corpus_id": "hizo-houyaku",
          "context": "た『大日経』（入曼荼羅品）にこう言っています、「その時に毘盧遮那世尊は、一切如来一体速疾力三昧という禅定に入って、自ら悟った",
          "context_position": 68247,
          "sanskrit_in_context": []
        },
        {
          "corpus_id": "hizo-houyaku",
          "context": "智なるがゆえに、羯磨智と名づけるのです。中央の大日如来・毘盧遮那仏は、法界体性智を成ずるに由るもので、これを根本智といいます",
          "context_position": 69892,
          "sanskrit_in_context": []
        },
        {
          "corpus_id": "hizo-houyaku",
          "context": "を証して、普賢の一切の行願を満足します。このゆえに、『大毘盧遮那経』成就悉地品にこう言っています、〈このような真実心は、前仏",
          "context_position": 72230,
          "sanskrit_in_context": []
        },
        {
          "corpus_id": "hizo-houyaku",
          "context": "達し、諸仏の法身を覚り、法界体性智を証すること、そして大毘盧遮那仏の自性身・受用身・変化身・等流身を成ずることなのです。行人",
          "context_position": 72787,
          "sanskrit_in_context": []
        },
        {
          "corpus_id": "hizo-houyaku",
          "context": "法を修さねばなりません。 第十住心の典拠 このゆえに『大毘盧遮那経』（大日経）にこう言っています、〈悉地は心より生ず〉と。 ",
          "context_position": 72903,
          "sanskrit_in_context": []
        },
        {
          "corpus_id": "hizo-houyaku",
          "context": "て本尊の身を成就することができるのです。 このゆえに『大毘盧遮那経』供養次第法にこう言っています、〈もし勢力の広く増益するこ",
          "context_position": 73105,
          "sanskrit_in_context": []
        },
        {
          "corpus_id": "hizo-houyaku",
          "context": "ましょう。だから、『金剛頂経』にこう説いています、「この毘盧遮那の三摩地の法は、まだ灌頂の儀式を済ませていない者に対しては、",
          "context_position": 74103,
          "sanskrit_in_context": []
        }
      ]
    },
    {
      "term": "阿字",
      "term_kana": "",
      "sanskrit": "a-kāra",
      "definition": "密教根本字。梵語五十字門の最初の字。本不生を象徴。",
      "kaimyo_suitable": false,
      "kaimyo_chars": [],
      "occurrence_count": 14,
      "occurrences": [
        {
          "corpus_id": "hizo-houyaku",
          "context": "わち、心は本より不生不滅という本性なのだと覚ること、これこそ阿字門に入り、次第に真言の悟りに近づいていくことなのです。 こう",
          "context_position": 51936,
          "sanskrit_in_context": []
        },
        {
          "corpus_id": "hizo-houyaku",
          "context": "光は大きくなり十五日になると円い姿になります。 阿字本不生と阿字の五転 このゆえに行者は、阿字を観ずる場合、初めは心の一分の",
          "context_position": 70586,
          "sanskrit_in_context": []
        },
        {
          "corpus_id": "hizo-houyaku",
          "context": "い姿になります。 阿字本不生と阿字の五転 このゆえに行者は、阿字を観ずる場合、初めは心の一分の明相を起こし、次第にその明相は",
          "context_position": 70601,
          "sanskrit_in_context": []
        },
        {
          "corpus_id": "hizo-houyaku",
          "context": "に満月のような、生死を越えた仏智を証するのです。 凡そ仏教で阿字というのは、一切諸法の、本より不生不滅なる義を示すものであり",
          "context_position": 70672,
          "sanskrit_in_context": []
        },
        {
          "corpus_id": "hizo-houyaku",
          "context": "る義を示すものであります。 『大日経疏』第十四によると、この阿字を釈するのに五通りあります。一に阿字（短声）でこれは菩提心の",
          "context_position": 70724,
          "sanskrit_in_context": []
        },
        {
          "corpus_id": "hizo-houyaku",
          "context": "疏』第十四によると、この阿字を釈するのに五通りあります。一に阿字（短声）でこれは菩提心の義です。二つに阿字（引声）で菩提行の",
          "context_position": 70742,
          "sanskrit_in_context": []
        },
        {
          "corpus_id": "hizo-houyaku",
          "context": "通りあります。一に阿字（短声）でこれは菩提心の義です。二つに阿字（引声）で菩提行の義です。三つに暗字（短声）で、これは証菩提",
          "context_position": 70763,
          "sanskrit_in_context": []
        },
        {
          "corpus_id": "hizo-houyaku",
          "context": "地）を開くことであり、同時に菩提心を開くことであって、初めの阿字のごとく菩提心の義に当ります。次に「示」は仏智見を示すことで",
          "context_position": 70947,
          "sanskrit_in_context": []
        },
        {
          "corpus_id": "hizo-houyaku",
          "context": "心の義に当ります。次に「示」は仏智見を示すことであり、第二の阿字のごとく菩提行の義に当ります。「悟」の字は、仏智見を悟ること",
          "context_position": 70985,
          "sanskrit_in_context": []
        },
        {
          "corpus_id": "hizo-houyaku",
          "context": "のことをうまくはこべる仏陀の智慧）を円満する義に当ります。 阿字観 阿字はこれ菩提心の義であることを讃嘆する頌にこう言ってい",
          "context_position": 71136,
          "sanskrit_in_context": []
        },
        {
          "corpus_id": "hizo-houyaku",
          "context": "うまくはこべる仏陀の智慧）を円満する義に当ります。 阿字観 阿字はこれ菩提心の義であることを讃嘆する頌にこう言っています。 ",
          "context_position": 71140,
          "sanskrit_in_context": []
        },
        {
          "corpus_id": "hizo-houyaku",
          "context": "。 八葉の白い蓮華が、自分の前一肘の所にあり、その月輪の中に阿字が素くかがやいて炳現しています。 両手を金剛縛に結んで、その",
          "context_position": 71200,
          "sanskrit_in_context": []
        },
        {
          "corpus_id": "hizo-houyaku",
          "context": "を得る仏の智慧）を自心の中に招き入れると観想しなさい。 この阿字の実義を会得したものはみな、決定してこれを観じ、当に円明な浄",
          "context_position": 71295,
          "sanskrit_in_context": []
        },
        {
          "corpus_id": "hizo-houyaku",
          "context": "心月のおもかげを見るようになれば、これを、〈真実の勝義諦たる阿字の当相を見る〉と名づけます。もし日常いつもこれを見るようにな",
          "context_position": 71381,
          "sanskrit_in_context": []
        }
      ]
    },
    {
      "term": "三摩地",
      "term_kana": "",
      "sanskrit": "samādhi",
      "definition": "禅定。心を一境に住して散乱を離れた状態。",
      "kaimyo_suitable": false,
      "kaimyo_chars": [],
      "occurrence_count": 13,
      "occurrences": [
        {
          "corpus_id": "hizo-houyaku",
          "context": "一切義成就菩薩は、一切如来の驚覚に由って、その場で阿娑婆那伽三摩地（無識身三摩地）より起って、一切如来を礼拝してもうされました",
          "context_position": 65285,
          "sanskrit_in_context": []
        },
        {
          "corpus_id": "hizo-houyaku",
          "context": "は、一切如来の驚覚に由って、その場で阿娑婆那伽三摩地（無識身三摩地）より起って、一切如来を礼拝してもうされました。〈世尊如来よ",
          "context_position": 65292,
          "sanskrit_in_context": []
        },
        {
          "corpus_id": "hizo-houyaku",
          "context": "また、この『大日経』には、百字輪とか十二字などの真言の観法や三摩地法門があり、また『金剛頂経』にも、金剛界三十七尊とか、四智印",
          "context_position": 68518,
          "sanskrit_in_context": []
        },
        {
          "corpus_id": "hizo-houyaku",
          "context": "門があり、また『金剛頂経』にも、金剛界三十七尊とか、四智印の三摩地等があります。すなわちこれらは、大日如来の極秘密三昧なのです",
          "context_position": 68552,
          "sanskrit_in_context": []
        },
        {
          "corpus_id": "hizo-houyaku",
          "context": "とはできないのです。 ◇ ［以下に続く『菩提心論』の文は、「三摩地段」といわれ、自心の探究を徹底的に深めてゆく観想法を述べた部",
          "context_position": 68651,
          "sanskrit_in_context": []
        },
        {
          "corpus_id": "hizo-houyaku",
          "context": "註）］ 竜猛菩薩の『菩提心論』にこう言っています。 「第三に三摩地の菩提心というのは、真言行人がこのように観察しおわって、どの",
          "context_position": 68884,
          "sanskrit_in_context": []
        },
        {
          "corpus_id": "hizo-houyaku",
          "context": "智慧の境地）とも申します。 これこそ、種々の無量の宝を含んだ三摩地（境地）であり、あたかも満月が皓々とすべてを照らすような状態",
          "context_position": 69400,
          "sanskrit_in_context": []
        },
        {
          "corpus_id": "hizo-houyaku",
          "context": "ような真実心は、前仏がすでに宣説したもう所であります〉と。 三摩地法 問う、前に、二乗（小乗）の人は、まだ法執（五蘊等の物のと",
          "context_position": 72282,
          "sanskrit_in_context": []
        },
        {
          "corpus_id": "hizo-houyaku",
          "context": "かし今また五相とか三密など有相（目にみえる形）の方法を設けて三摩地の菩提心を修行させるのは、法執（五蘊等の法は実在すると見る執",
          "context_position": 72369,
          "sanskrit_in_context": []
        },
        {
          "corpus_id": "hizo-houyaku",
          "context": "経て仏位（仏陀の位）に入っていくのであります。 すなわちこの三摩地というのは、よく諸仏の自性に達し、諸仏の法身を覚り、法界体性",
          "context_position": 72740,
          "sanskrit_in_context": []
        },
        {
          "corpus_id": "hizo-houyaku",
          "context": "、もし心が決定して教えのごとく修行すれば、その座を起たずして三摩地が現前します。まさにここにおいて本尊の身を成就することができ",
          "context_position": 73057,
          "sanskrit_in_context": []
        },
        {
          "corpus_id": "hizo-houyaku",
          "context": "にこう言っています。 もし人あって、仏慧を求めて、 菩提心の三摩地（妄念をはなれて心を一ヶ所に集中し、寂静な心に置く）に通達す",
          "context_position": 73412,
          "sanskrit_in_context": []
        },
        {
          "corpus_id": "hizo-houyaku",
          "context": "う。だから、『金剛頂経』にこう説いています、「この毘盧遮那の三摩地の法は、まだ灌頂の儀式を済ませていない者に対しては、わずか一",
          "context_position": 74106,
          "sanskrit_in_context": []
        }
      ]
    },
    {
      "term": "大悲",
      "term_kana": "",
      "sanskrit": "mahā-karuṇā",
      "definition": "仏の大いなる慈悲。一切衆生を救う心。",
      "kaimyo_suitable": true,
      "kaimyo_chars": [
        "大",
        "悲"
      ],
      "occurrence_count": 9,
      "occurrences": [
        {
          "corpus_id": "hizo-houyaku",
          "context": "ました、「仏教で罪を断ずる場合二種のやり方があります。一つは大悲の門で二つには大智の門です。大悲の門では、法を犯した者を寛大",
          "context_position": 34199,
          "sanskrit_in_context": []
        },
        {
          "corpus_id": "hizo-houyaku",
          "context": "種のやり方があります。一つは大悲の門で二つには大智の門です。大悲の門では、法を犯した者を寛大に扱って、罪を咎めることをゆるや",
          "context_position": 34215,
          "sanskrit_in_context": []
        },
        {
          "corpus_id": "hizo-houyaku",
          "context": "いているのは『涅槃経』や『薩遮尼乾子経』のような経典ですし、大悲の門は、『地蔵十輪経』などがそれに当ります。大悲の門では破戒",
          "context_position": 34336,
          "sanskrit_in_context": []
        },
        {
          "corpus_id": "hizo-houyaku",
          "context": "経典ですし、大悲の門は、『地蔵十輪経』などがそれに当ります。大悲の門では破戒の僧尼であっても寛大に扱います。出家得道し、これ",
          "context_position": 34360,
          "sanskrit_in_context": []
        },
        {
          "corpus_id": "hizo-houyaku",
          "context": "ず慈悲の心に基いています。慈悲のうち、大慈は人々に楽を与え、大悲は人々の苦しみを抜くものです。そして、苦を抜き楽を与える根本",
          "context_position": 36619,
          "sanskrit_in_context": []
        },
        {
          "corpus_id": "hizo-houyaku",
          "context": "やめます。この住心の人は、平等を見る真実の智慧と、差別を見る大悲の働きとの二智によって、一如平等の理を見て、円満なさとりに到",
          "context_position": 51011,
          "sanskrit_in_context": []
        },
        {
          "corpus_id": "hizo-houyaku",
          "context": "、心と虚空界と菩提との三種は別なものではありません。これらは大悲を根本とし、方便波羅蜜が満足されるのです。この故に秘密主よ、",
          "context_position": 57464,
          "sanskrit_in_context": []
        },
        {
          "corpus_id": "hizo-houyaku",
          "context": "が無窮（妙えなるはたらきはきわまりない）なのです。この大智・大悲の心を具える者だけが、説法し、自らをも他をも、ともに利益する",
          "context_position": 66614,
          "sanskrit_in_context": []
        },
        {
          "corpus_id": "hizo-houyaku",
          "context": "ためにしばられていて、その真相が見えないのです。そこで諸仏は大悲心の上から、善巧方便の智をもって、この甚深秘密瑜伽の観（はな",
          "context_position": 69094,
          "sanskrit_in_context": []
        }
      ]
    },
    {
      "term": "心王",
      "term_kana": "",
      "sanskrit": "citta-rāja",
      "definition": "八識の根本識。心の主体・統括者。",
      "kaimyo_suitable": false,
      "kaimyo_chars": [],
      "occurrence_count": 6,
      "occurrences": [
        {
          "corpus_id": "hizo-houyaku",
          "context": "として歎くのです。 第七住心の立場にあっては、我々の主体たる心王は、束縛から解放されて自在であり、本性の水を体得できるのです",
          "context_position": 50905,
          "sanskrit_in_context": []
        },
        {
          "corpus_id": "hizo-houyaku",
          "context": "から解放されて自在であり、本性の水を体得できるのです。そして心王に外から付着している種々の心の働きは、もはや動揺したり汚濁し",
          "context_position": 50941,
          "sanskrit_in_context": []
        },
        {
          "corpus_id": "hizo-houyaku",
          "context": "この文を釈してこういっています、「ここで心主といっているのは心王のことです。存在の有とか無とかに滞らないので、心に罣疑（こだ",
          "context_position": 51395,
          "sanskrit_in_context": []
        },
        {
          "corpus_id": "hizo-houyaku",
          "context": "きるのです。それゆえ、〈心主が自在だ〉というのです。ここで〈心王が自在〉というのは、浄菩提心がさらに一転の開明をして前の住心",
          "context_position": 51483,
          "sanskrit_in_context": []
        },
        {
          "corpus_id": "hizo-houyaku",
          "context": "さらに一転の開明をして前の住心を超えることを明かしています。心王は、恰も池の水の性質が本来清浄であるようなものです。そして心",
          "context_position": 51530,
          "sanskrit_in_context": []
        },
        {
          "corpus_id": "hizo-houyaku",
          "context": "が、しかし水自体はそうではなく先にもあとにも存在するのです。心王もまたこれと同じです。心の前後際はありません。過去も未来も変",
          "context_position": 51787,
          "sanskrit_in_context": []
        }
      ]
    },
    {
      "term": "本不生",
      "term_kana": "",
      "sanskrit": "ādyanutpāda",
      "definition": "一切法の本来不生不滅。阿字本不生の核となる教義。",
      "kaimyo_suitable": false,
      "kaimyo_chars": [],
      "occurrence_count": 6,
      "occurrences": [
        {
          "corpus_id": "hizo-houyaku",
          "context": "密主よ、彼はこのように無我を捨て、心主が自在であって、自心の本不生を覚ります。何をもっての故にとならば、秘密主よ、心は過去にさ",
          "context_position": 51265,
          "sanskrit_in_context": []
        },
        {
          "corpus_id": "hizo-houyaku",
          "context": "すから、心の本来の清浄な性質を明らかに示した時にはじめて心の本不生を覚るのです。なぜかというと、心というものは常に変化していて",
          "context_position": 51633,
          "sanskrit_in_context": []
        },
        {
          "corpus_id": "hizo-houyaku",
          "context": "まった時の水のように、常住であり、生滅は無いのです。この心の本不生、すなわち、心は本より不生不滅という本性なのだと覚ること、こ",
          "context_position": 51900,
          "sanskrit_in_context": []
        },
        {
          "corpus_id": "hizo-houyaku",
          "context": "かれています」と。 （弘法大師空海の言葉に戻って）いまここで本不生と言っているのは、不生・不滅、不断・不常、不一・不異、不去・",
          "context_position": 52074,
          "sanskrit_in_context": []
        },
        {
          "corpus_id": "hizo-houyaku",
          "context": "秘密主よ、彼はこのように無我を捨てて心主が自在となり、自心の本不生際を覚るのです。なぜかといえば、秘密主よ、心の前後際はともに",
          "context_position": 52712,
          "sanskrit_in_context": []
        },
        {
          "corpus_id": "hizo-houyaku",
          "context": "禅定に入って、自ら悟った法界体性三昧を説いて言いました。〈我本不生を覚り、語言の道を出過し、諸過を解脱することを得たり。因縁を",
          "context_position": 68297,
          "sanskrit_in_context": []
        }
      ]
    },
    {
      "term": "三密",
      "term_kana": "",
      "sanskrit": "trīṇi guhyāni",
      "definition": "身密（kāya-guhya）・口密（vāk-guhya）・意密（mano-guhya）。仏の三業を行者が修して即身成仏に至る道。",
      "kaimyo_suitable": true,
      "kaimyo_chars": [
        "密"
      ],
      "occurrence_count": 4,
      "occurrences": [
        {
          "corpus_id": "hizo-houyaku",
          "context": "す。 五相成身観 凡そ真言の瑜伽の観行を修習する人は、まさに三密の行を修し、五相成身の義を悟るべきであります。 初めに三密に",
          "context_position": 71562,
          "sanskrit_in_context": []
        },
        {
          "corpus_id": "hizo-houyaku",
          "context": "に三密の行を修し、五相成身の義を悟るべきであります。 初めに三密について述べますと、三密とは一には身密で、行者が手に印契を結",
          "context_position": 71591,
          "sanskrit_in_context": []
        },
        {
          "corpus_id": "hizo-houyaku",
          "context": "身の義を悟るべきであります。 初めに三密について述べますと、三密とは一には身密で、行者が手に印契を結び、聖衆をお招きするなど",
          "context_position": 71603,
          "sanskrit_in_context": []
        },
        {
          "corpus_id": "hizo-houyaku",
          "context": "）があるから成仏できない、と申しました。しかし今また五相とか三密など有相（目にみえる形）の方法を設けて三摩地の菩提心を修行さ",
          "context_position": 72348,
          "sanskrit_in_context": []
        }
      ]
    },
    {
      "term": "阿字本不生",
      "term_kana": "",
      "sanskrit": "ā-di-an-utpāda",
      "definition": "密教根本教義。阿字（a-kāra）が本来不生（不滅）であることを観じ、万物の本源を悟る。",
      "kaimyo_suitable": false,
      "kaimyo_chars": [],
      "occurrence_count": 1,
      "occurrences": [
        {
          "corpus_id": "hizo-houyaku",
          "context": "、次第に月の光は大きくなり十五日になると円い姿になります。 阿字本不生と阿字の五転 このゆえに行者は、阿字を観ずる場合、初めは心の",
          "context_position": 70580,
          "sanskrit_in_context": []
        }
      ]
    },
    {
      "term": "即身",
      "term_kana": "",
      "sanskrit": "sa-deha",
      "definition": "即身成仏の略。父母所生の身のまま現生で仏となる。",
      "kaimyo_suitable": false,
      "kaimyo_chars": [],
      "occurrence_count": 0,
      "occurrences": []
    },
    {
      "term": "即身成仏",
      "term_kana": "",
      "sanskrit": "sa-deha-prāpti-buddhatva",
      "definition": "空海『即身成仏義』中心教義。父母所生の身のまま、現生で仏となる密教の道。",
      "kaimyo_suitable": true,
      "kaimyo_chars": [
        "成",
        "仏"
      ],
      "occurrence_count": 0,
      "occurrences": []
    },
    {
      "term": "大空三昧",
      "term_kana": "",
      "sanskrit": "mahā-śūnyatā-samādhi",
      "definition": "大空（一切法空）を観ずる三昧。密教の高次禅定。",
      "kaimyo_suitable": false,
      "kaimyo_chars": [],
      "occurrence_count": 0,
      "occurrences": []
    },
    {
      "term": "智剣",
      "term_kana": "",
      "sanskrit": "jñāna-khaḍga",
      "definition": "煩悩を断ずる智慧の剣。文殊菩薩・不動明王の象徴。",
      "kaimyo_suitable": true,
      "kaimyo_chars": [
        "智",
        "剣"
      ],
      "occurrence_count": 0,
      "occurrences": []
    },
    {
      "term": "無縁慈悲",
      "term_kana": "",
      "sanskrit": "an-ārambaṇa-karuṇā",
      "definition": "対象を限定せず、すべての衆生に注がれる無条件の大悲。",
      "kaimyo_suitable": true,
      "kaimyo_chars": [
        "慈",
        "悲"
      ],
      "occurrence_count": 0,
      "occurrences": []
    },
    {
      "term": "玄機",
      "term_kana": "",
      "sanskrit": "—",
      "definition": "玄妙なる機関・機微。密教の深秘の働き。漢語起源（『荘子』『老子』由来）。",
      "kaimyo_suitable": true,
      "kaimyo_chars": [
        "玄",
        "機"
      ],
      "occurrence_count": 0,
      "occurrences": []
    }
  ]
}